mdict/__init__.py
mdict/ciphers/__init__.py
mdict/ciphers/ripemd128.py
mdict/ciphers/salsa20.py
mdict/core/__init__.py
mdict/core/index.py
mdict/core/mdict.py
mdict_py-0.1a4.dist-info/LICENSE
mdict_py-0.1a4.dist-info/METADATA
mdict_py-0.1a4.dist-info/WHEEL
mdict_py-0.1a4.dist-info/top_level.txt
mdict_py-0.1a4.dist-info/RECORD
